cbf_opt/__init__.py
cbf_opt/asif.py
cbf_opt/cbf.py
cbf_opt/dynamics.py
cbf_opt/utils.py
cbf_opt/tests/__init__.py
cbf_opt/tests/test_asif.py
cbf_opt/tests/test_cbf.py
cbf_opt/tests/test_dynamics.py
cbf_opt-0.6.0.dist-info/METADATA
cbf_opt-0.6.0.dist-info/WHEEL
cbf_opt-0.6.0.dist-info/top_level.txt
cbf_opt-0.6.0.dist-info/RECORD
